api_sos/__init__.py
api_sos/api_sos.py
api_sos/commands.py
api_sos/entity.py
api_sos/generate.py
api_sos/main.py
api_sos/utils.py
api_sos/tests/test_api_sos.py
api_sos/tests/test_utils.py
api_sos-1.1.0.dist-info/METADATA
api_sos-1.1.0.dist-info/WHEEL
api_sos-1.1.0.dist-info/entry_points.txt
api_sos-1.1.0.dist-info/RECORD
