Metadata-Version: 2.4
Name: api-sos
Version: 1.1.0
Summary: Add your description here
Requires-Python: >=3.12
Requires-Dist: aiohttp>=3.11.12
Requires-Dist: click>=8.1.8
Requires-Dist: faker>=36.1.1
Requires-Dist: jinja2>=3.1.6
Requires-Dist: loguru>=0.7.3
Requires-Dist: openapi-spec-validator>=0.7.1
Requires-Dist: prance>=23.6.21.0
Requires-Dist: pydantic>=2.10.6
Requires-Dist: ruamel-yaml>=0.18.10
